mkBot/__init__.py
mkBot/mkBot.py
mkBot-1.0.0.dist-info/LICENSE
mkBot-1.0.0.dist-info/METADATA
mkBot-1.0.0.dist-info/WHEEL
mkBot-1.0.0.dist-info/top_level.txt
mkBot-1.0.0.dist-info/RECORD
